[
  {
    "id": 405028,
    "cover": {
      "id": 569403,
      "image_id": "coc7cr"
    },
    "name": "Meccha Chameleon",
    "slug": "meccha-chameleon--1"
  },
  {
    "id": 141114,
    "cover": {
      "id": 498347,
      "image_id": "coaoiz"
    },
    "name": "007 First Light",
    "slug": "007-first-light",
    "total_rating": 79.84785248751527
  },
  {
    "id": 308535,
    "cover": {
      "id": 559609,
      "image_id": "cobzsp"
    },
    "name": "Neverness to Everness",
    "slug": "neverness-to-everness",
    "total_rating": 57.11799609353869
  },
  {
    "id": 348330,
    "cover": {
      "id": 528971,
      "image_id": "cobc5n"
    },
    "name": "Forza Horizon 6",
    "slug": "forza-horizon-6",
    "total_rating": 85.09071499281843
  },
  {
    "id": 403674,
    "cover": {
      "id": 571298,
      "image_id": "coc8te"
    },
    "name": "Don’t Sleep with the Fishes",
    "slug": "dont-sleep-with-the-fishes"
  },
  {
    "id": 361855,
    "cover": {
      "id": 480825,
      "image_id": "coab09"
    },
    "name": "LEGO Batman: Legacy of the Dark Knight",
    "slug": "lego-batman-legacy-of-the-dark-knight",
    "total_rating": 86.9754001021264
  },
  {
    "id": 393398,
    "cover": {
      "id": 545399,
      "image_id": "cobotz"
    },
    "name": "Librarian: Tidy Up the Arcane Library!",
    "slug": "librarian-tidy-up-the-arcane-library",
    "total_rating": 83.26707790724241
  },
  {
    "id": 403497,
    "cover": {
      "id": 566449,
      "image_id": "coc52p"
    },
    "name": "Fortune Mill",
    "slug": "fortune-mill"
  },
  {
    "id": 320140,
    "cover": {
      "id": 417780,
      "image_id": "co8yd0"
    },
    "name": "Subnautica 2",
    "slug": "subnautica-2",
    "total_rating": 90.03710862727858
  },
  {
    "id": 361890,
    "cover": {
      "id": 565449,
      "image_id": "coc4ax"
    },
    "name": "World of Tanks: Heat",
    "slug": "world-of-tanks-heat",
    "total_rating": 78
  },
  {
    "id": 399673,
    "cover": {
      "id": 559237,
      "image_id": "cobzid"
    },
    "name": "The Amazing Digital Dating Sim",
    "slug": "the-amazing-digital-dating-sim",
    "total_rating": 100
  },
  {
    "id": 358534,
    "cover": {
      "id": 541422,
      "image_id": "coblri"
    },
    "name": "The Adventures of Elliot: The Millennium Tales",
    "slug": "the-adventures-of-elliot-the-millennium-tales",
    "total_rating": 77.33333333333333
  },
  {
    "id": 189781,
    "cover": {
      "id": 207401,
      "image_id": "co4g15"
    },
    "name": "Mina the Hollower",
    "slug": "mina-the-hollower",
    "total_rating": 88.20209138337071
  },
  {
    "id": 237780,
    "cover": {
      "id": 411162,
      "image_id": "co8t96"
    },
    "name": "Directive 8020",
    "slug": "directive-8020",
    "total_rating": 75.56534953765959
  },
  {
    "id": 305157,
    "cover": {
      "id": 563634,
      "image_id": "coc2wi"
    },
    "name": "Mixtape",
    "slug": "mixtape--1",
    "total_rating": 73.59015751406093
  },
  {
    "id": 314543,
    "cover": {
      "id": 500872,
      "image_id": "coaqh4"
    },
    "name": "Heroes of Might & Magic: Olden Era",
    "slug": "heroes-of-might-and-magic-olden-era",
    "total_rating": 79.93517265094137
  },
  {
    "id": 331215,
    "cover": {
      "id": 492422,
      "image_id": "coajye"
    },
    "name": "Saros",
    "slug": "saros",
    "total_rating": 84.71583305882089
  },
  {
    "id": 341400,
    "cover": {
      "id": 460041,
      "image_id": "co9uyx"
    },
    "name": "Voidling Bound",
    "slug": "voidling-bound--1",
    "total_rating": 80
  },
  {
    "id": 404400,
    "cover": {
      "id": 568251,
      "image_id": "coc6gr"
    },
    "name": "FIFA World Cup: Launch Edition",
    "slug": "fifa-world-cup-launch-edition"
  }
]